MANIFEST.in
README.md
quicktest.py
settings_test.py
setup.py
django_facebook_users.egg-info/PKG-INFO
django_facebook_users.egg-info/SOURCES.txt
django_facebook_users.egg-info/dependency_links.txt
django_facebook_users.egg-info/not-zip-safe
django_facebook_users.egg-info/requires.txt
django_facebook_users.egg-info/top_level.txt
facebook_users/__init__.py
facebook_users/__init__.pyc
facebook_users/admin.py
facebook_users/admin.pyc
facebook_users/factories.py
facebook_users/factories.pyc
facebook_users/models.py
facebook_users/models.pyc
facebook_users/tests.py
facebook_users/tests.pyc
facebook_users/migrations/0001_initial.py
facebook_users/migrations/0001_initial.pyc
facebook_users/migrations/0002_auto__chg_field_user_name.py
facebook_users/migrations/0002_auto__chg_field_user_name.pyc
facebook_users/migrations/0003_auto__add_field_user_first_name__add_field_user_last_name__add_field_u.py
facebook_users/migrations/0003_auto__add_field_user_first_name__add_field_user_last_name__add_field_u.pyc
facebook_users/migrations/0004_auto__chg_field_user_updated_time.py
facebook_users/migrations/0004_auto__chg_field_user_updated_time.pyc
facebook_users/migrations/__init__.py
facebook_users/migrations/__init__.pyc